{
    "type": "Movie",
    "imdbId": "tt5433140",
    "name": "Fast X",
    "image": "https://m.media-amazon.com/images/M/MV5BNzZmOTU1ZTEtYzVhNi00NzQxLWI5ZjAtNWNhNjEwY2E3YmZjXkEyXkFqcGdeQXVyODk4OTc3MTY@._V1_.jpg",
    "description": "Dom Toretto and his family are targeted by the vengeful son of drug kingpin Hernan Reyes.",
    "rating": 5.8,
    "certificate": "PG-13",
    "genre": [
        "Action",
        "Adventure",
        "Crime"
    ],
    "year": 2023,
    "time": "2h 21m",
    "signed": false,
    "hasASubtitle": "",
    "arDescription": "يتم استهداف دوم توريتو وعائلته من قبل الابن المنتقم لزعيم المخدرات هيرنان رييس.",
    "video": [],
    "related": [
        "tt0232500",
        "tt0322259",
        "tt0463985",
        "tt1013752",
        "tt1596343",
        "tt1905041",
        "tt2820852",
        "tt4630562",
        "tt6806448",
        "tt5433138"
    ]
}